Metadata-Version: 2.1
Name: metrace
Version: 0.0.1
Summary: UNKNOWN
Home-page: UNKNOWN
Author: sloev
Author-email: johannes.valbjorn@gmail.com
License: UNKNOWN
Keywords: metrace cpu memory trace
Platform: UNKNOWN
Classifier: Intended Audience :: Developers
Classifier: Natural Language :: English
Classifier: Programming Language :: Python :: 2.7
Classifier: Programming Language :: Python :: 3.5
Classifier: Programming Language :: Python :: 3.6
Classifier: Programming Language :: Python :: 3.7
